{"version":3,"kind":"Article","sha256":"ce76a540041772689bf84d6a83a583b0b929403739c94f9f533617b00a899236","slug":"schedule","location":"/schedule.md","dependencies":[],"frontmatter":{"title":"Draft Hackathon Schedule","content_includes_title":false,"authors":[{"nameParsed":{"literal":"Project Pythia Community","given":"Project Pythia","family":"Community"},"name":"Project Pythia Community","url":"https://projectpythia.org/","id":"contributors-myst-generated-uid-0"}],"open_access":true,"license":{"content":{"id":"CC-BY-4.0","url":"https://creativecommons.org/licenses/by/4.0/","name":"Creative Commons Attribution 4.0 International","free":true,"CC":true},"code":{"id":"Apache-2.0","url":"https://opensource.org/licenses/Apache-2.0","name":"Apache License 2.0","free":true,"osi":true}},"github":"https://github.com/projectpythia/pythia-cookoff-2026","copyright":"2026","affiliations":[{"id":"UAlbany","name":"University at Albany (SUNY)","department":"Atmospheric and Environmental Sciences","url":"https://www.albany.edu/daes"},{"id":"CISL","name":"NSF National Center for Atmospheric Research","department":"Computational and Information Systems Lab","url":"https://www.cisl.ucar.edu"},{"id":"Unidata","name":"NSF Unidata","url":"https://www.unidata.ucar.edu"},{"id":"Argonne","name":"Argonne National Laboratory","department":"Environmental Science Division","url":"https://www.anl.gov/evs"},{"id":"CarbonPlan","name":"CarbonPlan","url":"https://carbonplan.org"},{"id":"NVIDIA","name":"NVIDIA Corporation","url":"https://www.nvidia.com/"}],"source_url":"https://github.com/projectpythia/pythia-cookoff-2026/blob/main/schedule.md","edit_url":"https://github.com/projectpythia/pythia-cookoff-2026/edit/main/schedule.md","exports":[{"format":"md","filename":"schedule.md","url":"/pythia-cookoff-2026/build/schedule-aa8d87937bcef52f702f4cbe50c6db7b.md"}]},"mdast":{"type":"root","children":[{"type":"block","children":[{"type":"paragraph","position":{"start":{"line":3,"column":1},"end":{"line":3,"column":1}},"children":[{"type":"emphasis","position":{"start":{"line":3,"column":1},"end":{"line":3,"column":1}},"children":[{"type":"text","value":"This is a placeholder draft and will change.","position":{"start":{"line":3,"column":1},"end":{"line":3,"column":1}},"key":"kBTx0uNw6G"}],"key":"WLWEVUYbwq"}],"key":"asFLfypD3D"},{"type":"list","ordered":false,"spread":false,"position":{"start":{"line":5,"column":1},"end":{"line":8,"column":1}},"children":[{"type":"listItem","spread":true,"position":{"start":{"line":5,"column":1},"end":{"line":5,"column":1}},"children":[{"type":"paragraph","children":[{"type":"text","value":"All rooms are in the ","position":{"start":{"line":5,"column":1},"end":{"line":5,"column":1}},"key":"pHaYmZ1IoH"},{"type":"link","url":"https://scied.ucar.edu/visit","position":{"start":{"line":5,"column":1},"end":{"line":5,"column":1}},"children":[{"type":"text","value":"NCAR Mesa Laboratory","position":{"start":{"line":5,"column":1},"end":{"line":5,"column":1}},"key":"XFf1HQPrcX"}],"urlSource":"https://scied.ucar.edu/visit","key":"ohMUKgaalC"}],"key":"urkPtpChsu"}],"key":"e4vtEsmSZ6"},{"type":"listItem","spread":true,"position":{"start":{"line":6,"column":1},"end":{"line":8,"column":1}},"children":[{"type":"paragraph","children":[{"type":"text","value":"All times are Mountain Daylight Time, UTC-6 (local time in Boulder CO)","position":{"start":{"line":6,"column":1},"end":{"line":6,"column":1}},"key":"Vi8l6DY61S"}],"key":"wd7zUiMwky"}],"key":"fGQAoMdwC0"}],"key":"ThdnkQwZU5"},{"type":"heading","depth":2,"position":{"start":{"line":9,"column":1},"end":{"line":9,"column":1}},"children":[{"type":"text","value":"Monday June 15","position":{"start":{"line":9,"column":1},"end":{"line":9,"column":1}},"key":"uvDdtSgG4J"}],"identifier":"monday-june-15","label":"Monday June 15","html_id":"monday-june-15","implicit":true,"key":"ArI4U3snOM"},{"type":"list","ordered":false,"spread":false,"position":{"start":{"line":10,"column":1},"end":{"line":16,"column":1}},"children":[{"type":"listItem","spread":true,"position":{"start":{"line":10,"column":1},"end":{"line":10,"column":1}},"children":[{"type":"paragraph","children":[{"type":"text","value":"9 am: Welcome plenary (Main Seminar Room)","position":{"start":{"line":10,"column":1},"end":{"line":10,"column":1}},"key":"HGDv66uBaW"}],"key":"tAQfDehYta"}],"key":"w0D0dUVwot"},{"type":"listItem","spread":true,"position":{"start":{"line":11,"column":1},"end":{"line":11,"column":1}},"children":[{"type":"paragraph","children":[{"type":"text","value":"10 am: Project pitches (Main Seminar Room)","position":{"start":{"line":11,"column":1},"end":{"line":11,"column":1}},"key":"PE9LnoVQTe"}],"key":"OZmaBYJp6G"}],"key":"m8pB6O0TZX"},{"type":"listItem","spread":true,"position":{"start":{"line":12,"column":1},"end":{"line":12,"column":1}},"children":[{"type":"paragraph","children":[{"type":"text","value":"12 pm: Lunch (Cafeteria)","position":{"start":{"line":12,"column":1},"end":{"line":12,"column":1}},"key":"h1vcYJPvpW"}],"key":"QZBvjENy7C"}],"key":"RYTZyLZLlu"},{"type":"listItem","spread":true,"position":{"start":{"line":13,"column":1},"end":{"line":13,"column":1}},"children":[{"type":"paragraph","children":[{"type":"text","value":"1-4 pm: Hacking (Main Seminar Room and Breakout Rooms)","position":{"start":{"line":13,"column":1},"end":{"line":13,"column":1}},"key":"WrDQTL4Qk7"}],"key":"cd9ZVqtMpE"}],"key":"uj1Jv4t5OA"},{"type":"listItem","spread":true,"position":{"start":{"line":14,"column":1},"end":{"line":14,"column":1}},"children":[{"type":"paragraph","children":[{"type":"text","value":"4 pm: Afternoon debrief (Main Seminar Room)","position":{"start":{"line":14,"column":1},"end":{"line":14,"column":1}},"key":"UUholp7CIq"}],"key":"BAhHzzVOlS"}],"key":"zry2lwpswD"},{"type":"listItem","spread":true,"position":{"start":{"line":15,"column":1},"end":{"line":16,"column":1}},"children":[{"type":"paragraph","children":[{"type":"text","value":"5 pm: Adjourn","position":{"start":{"line":15,"column":1},"end":{"line":15,"column":1}},"key":"fRw27cZKMX"}],"key":"erNhVgyDr6"}],"key":"T8IOTGMR7X"}],"key":"Jbh3s6ijec"},{"type":"heading","depth":2,"position":{"start":{"line":17,"column":1},"end":{"line":17,"column":1}},"children":[{"type":"text","value":"Tuesday June 16","position":{"start":{"line":17,"column":1},"end":{"line":17,"column":1}},"key":"wGYBY8958T"}],"identifier":"tuesday-june-16","label":"Tuesday June 16","html_id":"tuesday-june-16","implicit":true,"key":"zoaEOnQhyG"},{"type":"list","ordered":false,"spread":false,"position":{"start":{"line":18,"column":1},"end":{"line":24,"column":1}},"children":[{"type":"listItem","spread":true,"position":{"start":{"line":18,"column":1},"end":{"line":18,"column":1}},"children":[{"type":"paragraph","children":[{"type":"text","value":"9 am: Morning check-in (Main Seminar Room)","position":{"start":{"line":18,"column":1},"end":{"line":18,"column":1}},"key":"GOVzYqzBej"}],"key":"IrZ27ARRRj"}],"key":"KeLaTZZNot"},{"type":"listItem","spread":true,"position":{"start":{"line":19,"column":1},"end":{"line":19,"column":1}},"children":[{"type":"paragraph","children":[{"type":"text","value":"9:30 am: Hacking (Breakout Rooms)","position":{"start":{"line":19,"column":1},"end":{"line":19,"column":1}},"key":"Q5bL6mwm1I"}],"key":"jfrmwyDaSX"}],"key":"MFdENNbFer"},{"type":"listItem","spread":true,"position":{"start":{"line":20,"column":1},"end":{"line":20,"column":1}},"children":[{"type":"paragraph","children":[{"type":"text","value":"12 pm: Lunch (Cafeteria)","position":{"start":{"line":20,"column":1},"end":{"line":20,"column":1}},"key":"w7cy3t5jG6"}],"key":"PDfG8JeOdw"}],"key":"YS4eBzuizl"},{"type":"listItem","spread":true,"position":{"start":{"line":21,"column":1},"end":{"line":21,"column":1}},"children":[{"type":"paragraph","children":[{"type":"text","value":"1 pm: Hacking (Breakout Rooms)","position":{"start":{"line":21,"column":1},"end":{"line":21,"column":1}},"key":"gHvv7J4ACI"}],"key":"cPeawoLmhQ"}],"key":"B4DBvLjGPA"},{"type":"listItem","spread":true,"position":{"start":{"line":22,"column":1},"end":{"line":22,"column":1}},"children":[{"type":"paragraph","children":[{"type":"text","value":"2:15 pm: Afternoon debrief (Main Seminar Room)","position":{"start":{"line":22,"column":1},"end":{"line":22,"column":1}},"key":"GOJKF2Vtpg"}],"key":"nDqflKPUzB"}],"key":"DDibMfLzH7"},{"type":"listItem","spread":true,"position":{"start":{"line":23,"column":1},"end":{"line":24,"column":1}},"children":[{"type":"paragraph","children":[{"type":"text","value":"3 pm: Adjourn early for optional activities (hike or excursion to downtown Boulder)","position":{"start":{"line":23,"column":1},"end":{"line":23,"column":1}},"key":"ul2Desw80L"}],"key":"J8PVydM305"}],"key":"geWvAD1l4T"}],"key":"F78bfrj0wR"},{"type":"heading","depth":2,"position":{"start":{"line":25,"column":1},"end":{"line":25,"column":1}},"children":[{"type":"text","value":"Wednesday June 17","position":{"start":{"line":25,"column":1},"end":{"line":25,"column":1}},"key":"t5GnGdTGnl"}],"identifier":"wednesday-june-17","label":"Wednesday June 17","html_id":"wednesday-june-17","implicit":true,"key":"WpQqWeuDQZ"},{"type":"list","ordered":false,"spread":false,"position":{"start":{"line":26,"column":1},"end":{"line":32,"column":1}},"children":[{"type":"listItem","spread":true,"position":{"start":{"line":26,"column":1},"end":{"line":26,"column":1}},"children":[{"type":"paragraph","children":[{"type":"text","value":"9 am: Morning check-in (Main Seminar Room)","position":{"start":{"line":26,"column":1},"end":{"line":26,"column":1}},"key":"BecvVDziqT"}],"key":"VzbfOHzZHl"}],"key":"kx3KlE4fKo"},{"type":"listItem","spread":true,"position":{"start":{"line":27,"column":1},"end":{"line":27,"column":1}},"children":[{"type":"paragraph","children":[{"type":"text","value":"10 am: Hacking (Breakout Rooms)","position":{"start":{"line":27,"column":1},"end":{"line":27,"column":1}},"key":"Ci1qT4BFun"}],"key":"opOap9jqry"}],"key":"awQJI5PPZ0"},{"type":"listItem","spread":true,"position":{"start":{"line":28,"column":1},"end":{"line":28,"column":1}},"children":[{"type":"paragraph","children":[{"type":"text","value":"12:30 pm: Lunch (Cafeteria)","position":{"start":{"line":28,"column":1},"end":{"line":28,"column":1}},"key":"HxAQ51tn7h"}],"key":"qo9uRZItsM"}],"key":"MiuQHmm3eX"},{"type":"listItem","spread":true,"position":{"start":{"line":29,"column":1},"end":{"line":29,"column":1}},"children":[{"type":"paragraph","children":[{"type":"text","value":"1:30 pm: Hacking (Breakout Rooms)","position":{"start":{"line":29,"column":1},"end":{"line":29,"column":1}},"key":"Q3jkeK60y8"}],"key":"i6lMpjG0X6"}],"key":"b3y9F1IPYV"},{"type":"listItem","spread":true,"position":{"start":{"line":30,"column":1},"end":{"line":30,"column":1}},"children":[{"type":"paragraph","children":[{"type":"text","value":"4 pm: Afternoon debrief (Main Seminar Room)","position":{"start":{"line":30,"column":1},"end":{"line":30,"column":1}},"key":"UeWvMQz3MG"}],"key":"UXCqT5xpee"}],"key":"U02n3MPPDB"},{"type":"listItem","spread":true,"position":{"start":{"line":31,"column":1},"end":{"line":32,"column":1}},"children":[{"type":"paragraph","children":[{"type":"text","value":"5 pm: Adjourn","position":{"start":{"line":31,"column":1},"end":{"line":31,"column":1}},"key":"gpg017pOfB"}],"key":"G6wOBwNjQR"}],"key":"AVrlV5FyCi"}],"key":"lCR27oDfR0"},{"type":"paragraph","position":{"start":{"line":33,"column":1},"end":{"line":33,"column":1}},"children":[{"type":"emphasis","position":{"start":{"line":33,"column":1},"end":{"line":33,"column":1}},"children":[{"type":"text","value":"Pythia Cookout (evening social) to follow, details TBD","position":{"start":{"line":33,"column":1},"end":{"line":33,"column":1}},"key":"Yrca8hXODC"}],"key":"RRCUPzQKO3"}],"key":"Is8HS6T2UW"},{"type":"heading","depth":2,"position":{"start":{"line":35,"column":1},"end":{"line":35,"column":1}},"children":[{"type":"text","value":"Thursday June 18","position":{"start":{"line":35,"column":1},"end":{"line":35,"column":1}},"key":"oY52OqkNMn"}],"identifier":"thursday-june-18","label":"Thursday June 18","html_id":"thursday-june-18","implicit":true,"key":"N2IMokeHuf"},{"type":"list","ordered":false,"spread":false,"position":{"start":{"line":36,"column":1},"end":{"line":40,"column":1}},"children":[{"type":"listItem","spread":true,"position":{"start":{"line":36,"column":1},"end":{"line":36,"column":1}},"children":[{"type":"paragraph","children":[{"type":"text","value":"9 am: Morning check-in (Main Seminar Room)","position":{"start":{"line":36,"column":1},"end":{"line":36,"column":1}},"key":"TC5jT25udz"}],"key":"zbdG5b9Djp"}],"key":"Z32d1gKxFY"},{"type":"listItem","spread":true,"position":{"start":{"line":37,"column":1},"end":{"line":37,"column":1}},"children":[{"type":"paragraph","children":[{"type":"text","value":"9:30 am: Hacking (Breakout Rooms)","position":{"start":{"line":37,"column":1},"end":{"line":37,"column":1}},"key":"iiJSahm84X"}],"key":"f3qU3eHbe9"}],"key":"Fkg454WNWr"},{"type":"listItem","spread":true,"position":{"start":{"line":38,"column":1},"end":{"line":38,"column":1}},"children":[{"type":"paragraph","children":[{"type":"text","value":"12:00 pm: Lunch (Cafeteria)","position":{"start":{"line":38,"column":1},"end":{"line":38,"column":1}},"key":"oBW17QYqnN"}],"key":"g1EF5Xd7Ml"}],"key":"ahtsaGNvUT"},{"type":"listItem","spread":true,"position":{"start":{"line":39,"column":1},"end":{"line":39,"column":1}},"children":[{"type":"paragraph","children":[{"type":"text","value":"1:00 Wrap-up plenary and presentations (Main Seminar Room)","position":{"start":{"line":39,"column":1},"end":{"line":39,"column":1}},"key":"dBPVbfELKj"}],"key":"F0efx7vD1e"}],"key":"ruO36QtYG0"},{"type":"listItem","spread":true,"position":{"start":{"line":40,"column":1},"end":{"line":40,"column":1}},"children":[{"type":"paragraph","children":[{"type":"text","value":"2:30 Adjourn","position":{"start":{"line":40,"column":1},"end":{"line":40,"column":1}},"key":"U01pADJE5q"}],"key":"IlGgZ2arFT"}],"key":"Ib0VKnZKF7"}],"key":"DQOGxBYhYe"}],"key":"RM1Rspyma8"}],"key":"a1PJo7uXr8"},"references":{"cite":{"order":[],"data":{}}},"footer":{"navigation":{"prev":{"title":"Pythia Cook-off 2026","url":"/","group":"Pythia Cook-off 2026"},"next":{"title":"Travel Information","url":"/travel","group":"Pythia Cook-off 2026"}}},"domain":"http://localhost:3000"}